proxybrokersps/__init__.py
proxybrokersps/api.py
proxybrokersps/checker.py
proxybrokersps/cli.py
proxybrokersps/errors.py
proxybrokersps/judge.py
proxybrokersps/negotiators.py
proxybrokersps/providers.py
proxybrokersps/proxy.py
proxybrokersps/resolver.py
proxybrokersps/server.py
proxybrokersps/utils.py
proxybrokersps/data/GeoLite2-Country.mmdb
proxybrokersps/data/__init__.py
proxybrokersps-0.0.2.dist-info/LICENSE
proxybrokersps-0.0.2.dist-info/METADATA
proxybrokersps-0.0.2.dist-info/WHEEL
proxybrokersps-0.0.2.dist-info/entry_points.txt
proxybrokersps-0.0.2.dist-info/top_level.txt
proxybrokersps-0.0.2.dist-info/RECORD
