Metadata-Version: 2.1
Name: proxybrokersps
Version: 0.0.2
Summary: [Finder/Checker/Server] Finds public proxies from multiple sources and concurrently checks them. Supports HTTP(S) and SOCKS4/5.
Home-page: https://github.com/Aa-ronT/ProxyBrokerSPS
Author: Aa-ronT
Author-email: aarontrading2@gmail.com
License: Apache License, Version 2.0
Keywords: proxy finder grabber scraper parser graber scrapper checker broker async asynchronous http https connect socks socks4 socks5
Platform: any
Classifier: Development Status :: 5 - Production/Stable
Classifier: Environment :: Console
Classifier: Environment :: Web Environment
Classifier: Intended Audience :: Developers
Classifier: Programming Language :: Python :: 3.5
Classifier: Programming Language :: Python :: 3.6
Classifier: Programming Language :: Python :: 3.7
Classifier: Programming Language :: Python :: 3.8
Classifier: Operating System :: POSIX
Classifier: Operating System :: MacOS :: MacOS X
Classifier: Operating System :: Microsoft :: Windows
Classifier: Topic :: Internet :: WWW/HTTP :: Indexing/Search
Classifier: Topic :: Internet :: Proxy Servers
Classifier: License :: OSI Approved :: Apache Software License
Requires-Python: >=3.5.3
License-File: LICENSE
Requires-Dist: aiohttp >=3.5.4
Requires-Dist: aiodns >=2.0.0
Requires-Dist: attrs ==19.1.0
Requires-Dist: maxminddb >=1.4.1
